odoo/addons/ssi_partner/README.rst
odoo/addons/ssi_partner/__init__.py
odoo/addons/ssi_partner/__manifest__.py
odoo/addons/ssi_partner/menu.xml
odoo/addons/ssi_partner/models/__init__.py
odoo/addons/ssi_partner/models/company_entity_type.py
odoo/addons/ssi_partner/models/company_ownership_type.py
odoo/addons/ssi_partner/models/partner_contact_group.py
odoo/addons/ssi_partner/models/res_partner.py
odoo/addons/ssi_partner/models/res_partner_ethnicity.py
odoo/addons/ssi_partner/models/res_partner_religion.py
odoo/addons/ssi_partner/security/ir.model.access.csv
odoo/addons/ssi_partner/security/ir_module_category_data.xml
odoo/addons/ssi_partner/security/res_group_data.xml
odoo/addons/ssi_partner/static/description/icon.png
odoo/addons/ssi_partner/views/company_entity_type_views.xml
odoo/addons/ssi_partner/views/company_ownership_type_views.xml
odoo/addons/ssi_partner/views/partner_contact_group_views.xml
odoo/addons/ssi_partner/views/res_bank_views.xml
odoo/addons/ssi_partner/views/res_country_group_views.xml
odoo/addons/ssi_partner/views/res_country_state_views.xml
odoo/addons/ssi_partner/views/res_country_views.xml
odoo/addons/ssi_partner/views/res_partner_bank_views.xml
odoo/addons/ssi_partner/views/res_partner_category_views.xml
odoo/addons/ssi_partner/views/res_partner_ethnicity_views.xml
odoo/addons/ssi_partner/views/res_partner_industry_views.xml
odoo/addons/ssi_partner/views/res_partner_religion_views.xml
odoo/addons/ssi_partner/views/res_partner_title_views.xml
odoo/addons/ssi_partner/views/res_partner_views.xml
odoo14_addon_ssi_partner-14.0.1.11.0.dist-info/METADATA
odoo14_addon_ssi_partner-14.0.1.11.0.dist-info/WHEEL
odoo14_addon_ssi_partner-14.0.1.11.0.dist-info/top_level.txt
odoo14_addon_ssi_partner-14.0.1.11.0.dist-info/RECORD
