Metadata-Version: 2.1
Name: odoo14-addon-ssi_partner
Version: 14.0.1.11.0
Summary: Partner App
Home-page: https://simetri-sinergi.id
Author: PT. Simetri Sinergi Indonesia, OpenSynergy Indonesia
License: AGPL-3
Classifier: Programming Language :: Python
Classifier: Framework :: Odoo
Classifier: Framework :: Odoo :: 14.0
Classifier: License :: OSI Approved :: GNU Affero General Public License v3
Requires-Python: >=3.6
Requires-Dist: odoo14-addon-partner-contact-birthdate
Requires-Dist: odoo14-addon-partner-contact-birthplace
Requires-Dist: odoo14-addon-partner-contact-gender
Requires-Dist: odoo14-addon-partner-contact-nationality
Requires-Dist: odoo14-addon-partner-contact-personal-information-page
Requires-Dist: odoo14-addon-ssi-master-data-mixin
Requires-Dist: odoo<14.1dev,>=14.0a
